func2llmtool/__init__.py
func2llmtool/_modidx.py
func2llmtool/core.py
func2llmtool/docments.py
func2llmtool-0.0.2.dist-info/licenses/LICENSE
func2llmtool-0.0.2.dist-info/METADATA
func2llmtool-0.0.2.dist-info/WHEEL
func2llmtool-0.0.2.dist-info/entry_points.txt
func2llmtool-0.0.2.dist-info/top_level.txt
func2llmtool-0.0.2.dist-info/RECORD
