Metadata-Version: 2.4
Name: func2llmtool
Version: 0.0.2
Summary: Turns a Python function into dictionary in the OpenAI standard you can attach as a tool to a LLM request.
Home-page: https://github.com/NumesSanguis/func2llmtool
Author: Stef van der Struijk
Author-email: stefstruijk@protonmail.ch
License: Apache-2.0
Keywords: nbdev jupyter notebook python
Classifier: Development Status :: 4 - Beta
Classifier: Intended Audience :: Developers
Classifier: Natural Language :: English
Classifier: Programming Language :: Python :: 3.9
Classifier: Programming Language :: Python :: 3.10
Classifier: Programming Language :: Python :: 3.11
Classifier: Programming Language :: Python :: 3.12
Classifier: Programming Language :: Python :: 3.13
Requires-Python: >=3.9
License-File: LICENSE
Provides-Extra: dev
Requires-Dist: litellm[caching]; extra == "dev"
Requires-Dist: numpydoc; extra == "dev"
Dynamic: author
Dynamic: author-email
Dynamic: classifier
Dynamic: description
Dynamic: description-content-type
Dynamic: home-page
Dynamic: keywords
Dynamic: license
Dynamic: license-file
Dynamic: provides-extra
Dynamic: requires-python
Dynamic: summary
